{"stats":{"minecraft:custom":{"minecraft:jump":142,"minecraft:open_chest":2,"minecraft:time_since_rest":88436,"minecraft:play_one_minute":88436,"minecraft:crouch_one_cm":110,"minecraft:damage_taken":30,"minecraft:leave_game":16,"minecraft:sprint_one_cm":15682,"minecraft:time_since_death":88436,"minecraft:walk_on_water_one_cm":88,"minecraft:walk_one_cm":36309,"minecraft:sneak_time":36,"minecraft:fall_one_cm":269,"minecraft:fly_one_cm":48745},"minecraft:used":{"minecraft:torch":4,"minecraft:stone":1}},"DataVersion":1957}